pkgversions/PkgVersions.py
pkgversions/__init__.py
pkgversions/resources/__init__.py
pkgversions/resources/loggingConfiguration.json
pkgversions-0.2.2.dist-info/LICENSE
pkgversions-0.2.2.dist-info/METADATA
pkgversions-0.2.2.dist-info/WHEEL
pkgversions-0.2.2.dist-info/entry_points.txt
pkgversions-0.2.2.dist-info/top_level.txt
pkgversions-0.2.2.dist-info/RECORD
