Metadata-Version: 2.1
Name: pkgversions
Version: 0.2.2
Summary: A build help tool
Home-page: https://github.com/hasii2011/pkgversions
Author-email: Humberto.A.Sanchez.II@gmail.com
License-File: LICENSE
Requires-Dist: click
